x_make_persistent_env_var_x/__init__.py
x_make_persistent_env_var_x/x_cls_make_persistent_env_var_x.py
x_make_persistent_env_var_x-12.0.0.dist-info/METADATA
x_make_persistent_env_var_x-12.0.0.dist-info/WHEEL
x_make_persistent_env_var_x-12.0.0.dist-info/top_level.txt
x_make_persistent_env_var_x-12.0.0.dist-info/RECORD
