Metadata-Version: 2.4
Name: x_make_persistent_env_var_x
Version: 12.0.0
Summary: Generic persistent environment variable setter for Windows (User scope).
Author-email: RRGM of the Primus Pilus Night Watch AI Corporation <eye4357@outlook.com>
License-Expression: MIT
